chat/__init__.py
chat/admin.py
chat/apps.py
chat/consumers.py
chat/middleware.py
chat/models.py
chat/routing.py
chat/serializers.py
chat/tests.py
chat/urls.py
chat/version.py
chat/views.py
chat/migrations/0001_initial.py
chat/migrations/0002_auto_20191214_2243.py
chat/migrations/0003_auto_20191214_2339.py
chat/migrations/0004_auto_20191214_2340.py
chat/migrations/__init__.py
testserver/__init__.py
testserver/asgi.py
testserver/routing.py
testserver/settings.py
testserver/urls.py
testserver/wsgi.py
djChat-0.1.dist-info/METADATA
djChat-0.1.dist-info/WHEEL
djChat-0.1.dist-info/entry_points.txt
djChat-0.1.dist-info/top_level.txt
djChat-0.1.dist-info/RECORD
